nemotron_table_structure_v1/__init__.py
nemotron_table_structure_v1/config.json
nemotron_table_structure_v1/model.py
nemotron_table_structure_v1/table_structure_v1.py
nemotron_table_structure_v1/utils.py
nemotron_table_structure_v1/post_processing/__init__.py
nemotron_table_structure_v1/post_processing/table_struct_pp.py
nemotron_table_structure_v1/post_processing/wbf.py
nemotron_table_structure_v1/yolox/__init__.py
nemotron_table_structure_v1/yolox/boxes.py
nemotron_table_structure_v1/yolox/darknet.py
nemotron_table_structure_v1/yolox/network_blocks.py
nemotron_table_structure_v1/yolox/yolo_fpn.py
nemotron_table_structure_v1/yolox/yolo_head.py
nemotron_table_structure_v1/yolox/yolo_pafpn.py
nemotron_table_structure_v1/yolox/yolox.py
nemotron_table_structure_v1-1.0.0.dist-info/METADATA
nemotron_table_structure_v1-1.0.0.dist-info/WHEEL
nemotron_table_structure_v1-1.0.0.dist-info/top_level.txt
nemotron_table_structure_v1-1.0.0.dist-info/RECORD
