Metadata-Version: 2.4
Name: nemotron-table-structure-v1
Version: 1.0.0
Summary: Nemotron Table Structure v1 - A specialized object detection model for table structure extraction
Author-email: NVIDIA Corporation <tviel@nvidia.com>
License: NVIDIA Open Model License
Project-URL: Homepage, https://huggingface.co/nvidia/nemotron-table-structure-v1
Project-URL: Repository, https://huggingface.co/nvidia/nemotron-table-structure-v1
Project-URL: Documentation, https://huggingface.co/nvidia/nemotron-table-structure-v1
Project-URL: Bug Tracker, https://huggingface.co/nvidia/nemotron-table-structure-v1/discussions
Keywords: table-structure,object-detection,yolox,nvidia,nemotron,pdf,document-processing,ocr
Classifier: Development Status :: 5 - Production/Stable
Classifier: Intended Audience :: Developers
Classifier: Intended Audience :: Science/Research
Classifier: License :: Other/Proprietary License
Classifier: Operating System :: OS Independent
Classifier: Programming Language :: Python :: 3
Classifier: Programming Language :: Python :: 3.8
Classifier: Programming Language :: Python :: 3.9
Classifier: Programming Language :: Python :: 3.10
Classifier: Programming Language :: Python :: 3.11
Classifier: Topic :: Scientific/Engineering :: Artificial Intelligence
Classifier: Topic :: Scientific/Engineering :: Image Recognition
Requires-Python: >=3.8
Requires-Dist: torch>=2.0.0
Requires-Dist: numpy>=1.21.0
Requires-Dist: matplotlib>=3.3.0
Requires-Dist: pandas>=1.3.0
Requires-Dist: Pillow>=8.0.0
Requires-Dist: huggingface_hub>=0.20.0
